mimic_hand_middleware/__init__.py
mimic_hand_middleware/cad_convert/mimic_palm_read/mimic_palm_read.py
mimic_hand_middleware/calibrate_gripper.py
mimic_hand_middleware/conversion_utils/P045/p04.py
mimic_hand_middleware/conversion_utils/P046/p046.py
mimic_hand_middleware/conversion_utils/__init__.py
mimic_hand_middleware/conversion_utils/hand_utils.py
mimic_hand_middleware/conversion_utils/recalculate_limits.py
mimic_hand_middleware/grasp_gui/grasp_gui.py
mimic_hand_middleware/gripper_controller.py
mimic_hand_middleware/hand_definitions/urdf/p45/base_link.stl
mimic_hand_middleware/hand_definitions/urdf/p45/converted.urdf
mimic_hand_middleware/hand_definitions/urdf/p45/middle_dp_v1_1.stl
mimic_hand_middleware/hand_definitions/urdf/p45/middle_mcp_v1_1.stl
mimic_hand_middleware/hand_definitions/urdf/p45/middle_mp_v1_1.stl
mimic_hand_middleware/hand_definitions/urdf/p45/middle_pp_v1_1.stl
mimic_hand_middleware/hand_definitions/urdf/p45/pinky_dp_v1_1.stl
mimic_hand_middleware/hand_definitions/urdf/p45/pinky_mcp_v1_1.stl
mimic_hand_middleware/hand_definitions/urdf/p45/pinky_mp_v1_1.stl
mimic_hand_middleware/hand_definitions/urdf/p45/pinky_pp_v1_1.stl
mimic_hand_middleware/hand_definitions/urdf/p45/ring_dp_v1_1.stl
mimic_hand_middleware/hand_definitions/urdf/p45/ring_dp_v1_2.stl
mimic_hand_middleware/hand_definitions/urdf/p45/ring_mcp_v1_1.stl
mimic_hand_middleware/hand_definitions/urdf/p45/ring_mcp_v1_2.stl
mimic_hand_middleware/hand_definitions/urdf/p45/ring_mp_v1_1.stl
mimic_hand_middleware/hand_definitions/urdf/p45/ring_mp_v1_2.stl
mimic_hand_middleware/hand_definitions/urdf/p45/ring_pp_v1_1.stl
mimic_hand_middleware/hand_definitions/urdf/p45/ring_pp_v1_2.stl
mimic_hand_middleware/hand_definitions/urdf/p45/thumb_cmc_v3_1.stl
mimic_hand_middleware/hand_definitions/urdf/p45/thumb_dp_v1_1.stl
mimic_hand_middleware/hand_definitions/urdf/p45/thumb_mp_v1_1.stl
mimic_hand_middleware/hand_definitions/urdf/p45/thumb_pp_v1_1.stl
mimic_hand_middleware-0.3.0.0.dist-info/METADATA
mimic_hand_middleware-0.3.0.0.dist-info/WHEEL
mimic_hand_middleware-0.3.0.0.dist-info/RECORD
