Metadata-Version: 2.1
Name: mimic_hand_middleware
Version: 0.3.0.0
Summary: Joint-to-motor level control API for mimic robotics AG's robotic hands.
License: Closed source
Author: Ben Forrai
Author-email: ben.forrai@mimicrobotics.com
Requires-Python: ==3.10.12
Classifier: License :: Other/Proprietary License
Classifier: Programming Language :: Python :: 3
Requires-Dist: click (>=8.0.0,<9.0.0)
Requires-Dist: defusedxml (>=0.7.1,<0.8.0)
Requires-Dist: matplotlib (>=3.0.0,<4.0.0)
Requires-Dist: mimic-hand-api (>=4.2.0,<5.0.0)
Requires-Dist: numpy (>=1.26.4,<2.0.0)
Requires-Dist: opencv-python
Requires-Dist: pandas (>=2.0.0,<3.0.0)
Requires-Dist: protobuf (>=5.28.3,<6.0.0)
Requires-Dist: pyserial (>=3.5,<4.0)
Requires-Dist: pyyaml (>=6.0.0,<7.0.0)
